bcachefs/__init__.py
bcachefs/bcachefs.py
bcachefs/c_bcachefs.cpython-37m-darwin.so
bcachefs-0.0.0.dist-info/AUTHORS
bcachefs-0.0.0.dist-info/LICENSE
bcachefs-0.0.0.dist-info/METADATA
bcachefs-0.0.0.dist-info/WHEEL
bcachefs-0.0.0.dist-info/top_level.txt
bcachefs-0.0.0.dist-info/RECORD
